{
  "code": "308170",
  "current_or_latest_name": "씨티알모빌리티",
  "name_history": [
    {
      "name": "센트랄모텍",
      "first_date": "2019-11-25",
      "last_date": "2023-04-26"
    },
    {
      "name": "씨티알모빌리티",
      "first_date": "2023-04-27",
      "last_date": "2026-02-20"
    }
  ],
  "markets": [
    "KOSPI"
  ],
  "market_history": [
    {
      "market": "KOSPI",
      "first_date": "2019-11-25",
      "last_date": "2026-02-20"
    }
  ],
  "first_date": "2019-11-25",
  "last_date": "2026-02-20",
  "trading_day_count": 1531,
  "available_years": [
    2019,
    2020,
    2021,
    2022,
    2023,
    2024,
    2025,
    2026
  ],
  "year_files": [
    "atlas/ohlcv_min_by_symbol_year/308/308170/2019.csv",
    "atlas/ohlcv_min_by_symbol_year/308/308170/2020.csv",
    "atlas/ohlcv_min_by_symbol_year/308/308170/2021.csv",
    "atlas/ohlcv_min_by_symbol_year/308/308170/2022.csv",
    "atlas/ohlcv_min_by_symbol_year/308/308170/2023.csv",
    "atlas/ohlcv_min_by_symbol_year/308/308170/2024.csv",
    "atlas/ohlcv_min_by_symbol_year/308/308170/2025.csv",
    "atlas/ohlcv_min_by_symbol_year/308/308170/2026.csv"
  ],
  "latest_close": 6410,
  "latest_marcap": 55190100000,
  "latest_market": "KOSPI",
  "status_inferred": "active_like",
  "status_inference_note": "Inferred only from FinanceData/marcap row presence, not an official listing/delisting status.",
  "price_data_source": "FinanceData/marcap",
  "source_repo_url": "https://github.com/FinanceData/marcap",
  "price_adjustment_status": "raw_unadjusted_marcap",
  "caveat": "Raw/unadjusted OHLC from FinanceData/marcap. Corporate actions are not adjusted unless explicitly added later."
}
