{
  "prefix": "178",
  "codes": [
    {
      "code": "178320",
      "name": "서진시스템",
      "profile_path": "atlas/symbol_profiles/178/178320.json",
      "available_years": [
        2017,
        2018,
        2019,
        2020,
        2021,
        2022,
        2023,
        2024,
        2025,
        2026
      ],
      "first_date": "2017-03-27",
      "last_date": "2026-02-20",
      "status_inferred": "active_like"
    },
    {
      "code": "178600",
      "name": "대동고려삼",
      "profile_path": "atlas/symbol_profiles/178/178600.json",
      "available_years": [
        2013,
        2014,
        2015,
        2016,
        2017,
        2018,
        2019,
        2020,
        2021,
        2022,
        2023,
        2024,
        2025,
        2026
      ],
      "first_date": "2013-12-20",
      "last_date": "2026-02-20",
      "status_inferred": "active_like"
    },
    {
      "code": "178780",
      "name": "일월지엠엘",
      "profile_path": "atlas/symbol_profiles/178/178780.json",
      "available_years": [
        2015,
        2016,
        2017,
        2018,
        2019,
        2020,
        2021,
        2022,
        2023,
        2024,
        2025,
        2026
      ],
      "first_date": "2015-06-30",
      "last_date": "2026-02-20",
      "status_inferred": "active_like"
    },
    {
      "code": "178920",
      "name": "PI첨단소재",
      "profile_path": "atlas/symbol_profiles/178/178920.json",
      "available_years": [
        2014,
        2015,
        2016,
        2017,
        2018,
        2019,
        2020,
        2021,
        2022,
        2023,
        2024,
        2025,
        2026
      ],
      "first_date": "2014-12-08",
      "last_date": "2026-02-20",
      "status_inferred": "active_like"
    }
  ]
}
