{
  "code": "003980",
  "current_or_latest_name": "한일합섬",
  "name_history": [
    {
      "name": "한일합섬",
      "first_date": "1995-05-02",
      "last_date": "2003-09-23"
    }
  ],
  "markets": [
    "KOSPI"
  ],
  "market_history": [
    {
      "market": "KOSPI",
      "first_date": "1995-05-02",
      "last_date": "2003-09-23"
    }
  ],
  "first_date": "1995-05-02",
  "last_date": "2003-09-23",
  "trading_day_count": 2233,
  "available_years": [
    1995,
    1996,
    1997,
    1998,
    1999,
    2000,
    2001,
    2002,
    2003
  ],
  "year_files": [
    "atlas/ohlcv_min_by_symbol_year/003/003980/1995.csv",
    "atlas/ohlcv_min_by_symbol_year/003/003980/1996.csv",
    "atlas/ohlcv_min_by_symbol_year/003/003980/1997.csv",
    "atlas/ohlcv_min_by_symbol_year/003/003980/1998.csv",
    "atlas/ohlcv_min_by_symbol_year/003/003980/1999.csv",
    "atlas/ohlcv_min_by_symbol_year/003/003980/2000.csv",
    "atlas/ohlcv_min_by_symbol_year/003/003980/2001.csv",
    "atlas/ohlcv_min_by_symbol_year/003/003980/2002.csv",
    "atlas/ohlcv_min_by_symbol_year/003/003980/2003.csv"
  ],
  "latest_close": 25,
  "latest_marcap": 1572234350,
  "latest_market": "KOSPI",
  "status_inferred": "inactive_or_delisted_like",
  "status_inference_note": "Inferred only from FinanceData/marcap row presence, not an official listing/delisting status.",
  "price_data_source": "FinanceData/marcap",
  "source_repo_url": "https://github.com/FinanceData/marcap",
  "price_adjustment_status": "raw_unadjusted_marcap",
  "caveat": "Raw/unadjusted OHLC from FinanceData/marcap. Corporate actions are not adjusted unless explicitly added later."
}
